{
  "session_type": "FP3",
  "session_name": "Practice 3",
  "year": 2023,
  "round": 2,
  "gp_name": "Saudi Arabian Grand Prix",
  "date": "2023-03-18",
  "track": "Jeddah",
  "country": "Saudi Arabia",
  "best_times": {
    "VER": 88.485,
    "SAR": 90.035,
    "NOR": 89.69,
    "GAS": 89.701,
    "PER": 89.098,
    "ALO": 89.483,
    "LEC": 89.588,
    "STR": 89.509,
    "MAG": 90.131,
    "TSU": 90.797,
    "ALB": 89.983,
    "ZHO": 89.917,
    "HUL": 89.933,
    "OCO": 89.953,
    "HAM": 89.568,
    "SAI": 89.761,
    "RUS": 89.811,
    "BOT": 90.317,
    "PIA": 89.698
  },
  "results": [
    {
      "position": null,
      "driver": "VER",
      "driver_number": 1,
      "team": "Red Bull Racing",
      "grid_position": null,
      "status": "",
      "points": 0
    },
    {
      "position": null,
      "driver": "SAR",
      "driver_number": 2,
      "team": "Williams",
      "grid_position": null,
      "status": "",
      "points": 0
    },
    {
      "position": null,
      "driver": "NOR",
      "driver_number": 4,
      "team": "McLaren",
      "grid_position": null,
      "status": "",
      "points": 0
    },
    {
      "position": null,
      "driver": "GAS",
      "driver_number": 10,
      "team": "Alpine",
      "grid_position": null,
      "status": "",
      "points": 0
    },
    {
      "position": null,
      "driver": "PER",
      "driver_number": 11,
      "team": "Red Bull Racing",
      "grid_position": null,
      "status": "",
      "points": 0
    },
    {
      "position": null,
      "driver": "ALO",
      "driver_number": 14,
      "team": "Aston Martin",
      "grid_position": null,
      "status": "",
      "points": 0
    },
    {
      "position": null,
      "driver": "LEC",
      "driver_number": 16,
      "team": "Ferrari",
      "grid_position": null,
      "status": "",
      "points": 0
    },
    {
      "position": null,
      "driver": "STR",
      "driver_number": 18,
      "team": "Aston Martin",
      "grid_position": null,
      "status": "",
      "points": 0
    },
    {
      "position": null,
      "driver": "MAG",
      "driver_number": 20,
      "team": "Haas F1 Team",
      "grid_position": null,
      "status": "",
      "points": 0
    },
    {
      "position": null,
      "driver": "DEV",
      "driver_number": 21,
      "team": "AlphaTauri",
      "grid_position": null,
      "status": "",
      "points": 0
    },
    {
      "position": null,
      "driver": "TSU",
      "driver_number": 22,
      "team": "AlphaTauri",
      "grid_position": null,
      "status": "",
      "points": 0
    },
    {
      "position": null,
      "driver": "ALB",
      "driver_number": 23,
      "team": "Williams",
      "grid_position": null,
      "status": "",
      "points": 0
    },
    {
      "position": null,
      "driver": "ZHO",
      "driver_number": 24,
      "team": "Alfa Romeo",
      "grid_position": null,
      "status": "",
      "points": 0
    },
    {
      "position": null,
      "driver": "HUL",
      "driver_number": 27,
      "team": "Haas F1 Team",
      "grid_position": null,
      "status": "",
      "points": 0
    },
    {
      "position": null,
      "driver": "OCO",
      "driver_number": 31,
      "team": "Alpine",
      "grid_position": null,
      "status": "",
      "points": 0
    },
    {
      "position": null,
      "driver": "HAM",
      "driver_number": 44,
      "team": "Mercedes",
      "grid_position": null,
      "status": "",
      "points": 0
    },
    {
      "position": null,
      "driver": "SAI",
      "driver_number": 55,
      "team": "Ferrari",
      "grid_position": null,
      "status": "",
      "points": 0
    },
    {
      "position": null,
      "driver": "RUS",
      "driver_number": 63,
      "team": "Mercedes",
      "grid_position": null,
      "status": "",
      "points": 0
    },
    {
      "position": null,
      "driver": "BOT",
      "driver_number": 77,
      "team": "Alfa Romeo",
      "grid_position": null,
      "status": "",
      "points": 0
    },
    {
      "position": null,
      "driver": "PIA",
      "driver_number": 81,
      "team": "McLaren",
      "grid_position": null,
      "status": "",
      "points": 0
    }
  ],
  "weather": {
    "air_temp": 27.070731707317076,
    "track_temp": 40.1719512195122,
    "humidity": 57.46341463414634,
    "rainfall": false,
    "wind_speed": 3.5353658536585364
  },
  "fetched_at": "2026-05-21T21:07:04.639557"
}