{
  "session_type": "FP1",
  "session_name": "Practice 1",
  "year": 2026,
  "round": 9,
  "gp_name": "British Grand Prix",
  "date": "2026-07-03",
  "track": "Silverstone",
  "country": "United Kingdom",
  "best_times": {
    "NOR": 90.288,
    "VER": 90.24,
    "BOR": 91.035,
    "HAD": 90.338,
    "GAS": 92.195,
    "PER": 92.241,
    "ANT": 89.473,
    "ALO": 92.957,
    "LEC": 89.859,
    "STR": 93.13,
    "ALB": 91.697,
    "HUL": 90.743,
    "LAW": 90.85,
    "OCO": 91.684,
    "LIN": 91.339,
    "COL": 90.966,
    "HAM": 89.26,
    "SAI": 91.684,
    "RUS": 89.938,
    "BOT": 92.15,
    "PIA": 90.147,
    "BEA": 91.373
  },
  "results": [
    {
      "position": null,
      "driver": "NOR",
      "driver_number": 1,
      "team": "McLaren",
      "grid_position": null,
      "status": "",
      "points": 0
    },
    {
      "position": null,
      "driver": "VER",
      "driver_number": 3,
      "team": "Red Bull Racing",
      "grid_position": null,
      "status": "",
      "points": 0
    },
    {
      "position": null,
      "driver": "BOR",
      "driver_number": 5,
      "team": "Audi",
      "grid_position": null,
      "status": "",
      "points": 0
    },
    {
      "position": null,
      "driver": "HAD",
      "driver_number": 6,
      "team": "Red Bull Racing",
      "grid_position": null,
      "status": "",
      "points": 0
    },
    {
      "position": null,
      "driver": "GAS",
      "driver_number": 10,
      "team": "Alpine",
      "grid_position": null,
      "status": "",
      "points": 0
    },
    {
      "position": null,
      "driver": "PER",
      "driver_number": 11,
      "team": "Cadillac",
      "grid_position": null,
      "status": "",
      "points": 0
    },
    {
      "position": null,
      "driver": "ANT",
      "driver_number": 12,
      "team": "Mercedes",
      "grid_position": null,
      "status": "",
      "points": 0
    },
    {
      "position": null,
      "driver": "ALO",
      "driver_number": 14,
      "team": "Aston Martin",
      "grid_position": null,
      "status": "",
      "points": 0
    },
    {
      "position": null,
      "driver": "LEC",
      "driver_number": 16,
      "team": "Ferrari",
      "grid_position": null,
      "status": "",
      "points": 0
    },
    {
      "position": null,
      "driver": "STR",
      "driver_number": 18,
      "team": "Aston Martin",
      "grid_position": null,
      "status": "",
      "points": 0
    },
    {
      "position": null,
      "driver": "ALB",
      "driver_number": 23,
      "team": "Williams",
      "grid_position": null,
      "status": "",
      "points": 0
    },
    {
      "position": null,
      "driver": "HUL",
      "driver_number": 27,
      "team": "Audi",
      "grid_position": null,
      "status": "",
      "points": 0
    },
    {
      "position": null,
      "driver": "LAW",
      "driver_number": 30,
      "team": "Racing Bulls",
      "grid_position": null,
      "status": "",
      "points": 0
    },
    {
      "position": null,
      "driver": "OCO",
      "driver_number": 31,
      "team": "Haas F1 Team",
      "grid_position": null,
      "status": "",
      "points": 0
    },
    {
      "position": null,
      "driver": "LIN",
      "driver_number": 41,
      "team": "Racing Bulls",
      "grid_position": null,
      "status": "",
      "points": 0
    },
    {
      "position": null,
      "driver": "COL",
      "driver_number": 43,
      "team": "Alpine",
      "grid_position": null,
      "status": "",
      "points": 0
    },
    {
      "position": null,
      "driver": "HAM",
      "driver_number": 44,
      "team": "Ferrari",
      "grid_position": null,
      "status": "",
      "points": 0
    },
    {
      "position": null,
      "driver": "SAI",
      "driver_number": 55,
      "team": "Williams",
      "grid_position": null,
      "status": "",
      "points": 0
    },
    {
      "position": null,
      "driver": "RUS",
      "driver_number": 63,
      "team": "Mercedes",
      "grid_position": null,
      "status": "",
      "points": 0
    },
    {
      "position": null,
      "driver": "BOT",
      "driver_number": 77,
      "team": "Cadillac",
      "grid_position": null,
      "status": "",
      "points": 0
    },
    {
      "position": null,
      "driver": "PIA",
      "driver_number": 81,
      "team": "McLaren",
      "grid_position": null,
      "status": "",
      "points": 0
    },
    {
      "position": null,
      "driver": "BEA",
      "driver_number": 87,
      "team": "Haas F1 Team",
      "grid_position": null,
      "status": "",
      "points": 0
    }
  ],
  "weather": {
    "air_temp": 22.023809523809526,
    "track_temp": 40.70119047619047,
    "humidity": 47.65714285714286,
    "rainfall": false,
    "wind_speed": 1.6583333333333332
  },
  "fetched_at": "2026-07-13T13:57:17.026979"
}