{
  "session_type": "FP3",
  "session_name": "Practice 3",
  "year": 2023,
  "round": 8,
  "gp_name": "Canadian Grand Prix",
  "date": "2023-06-17",
  "track": "Montr\u00e9al",
  "country": "Canada",
  "best_times": {
    "VER": 83.106,
    "GAS": 84.825,
    "PER": 85.857,
    "ALO": 84.483,
    "LEC": 83.397,
    "STR": 84.944,
    "SAR": 87.279,
    "MAG": 84.715,
    "DEV": 85.725,
    "TSU": 84.955,
    "ALB": 85.379,
    "ZHO": 86.75,
    "HUL": 85.14,
    "OCO": 86.84,
    "NOR": 85.198,
    "HAM": 85.087,
    "SAI": 84.765,
    "RUS": 85.435,
    "BOT": 84.988,
    "PIA": 85.191
  },
  "results": [
    {
      "position": null,
      "driver": "VER",
      "driver_number": 1,
      "team": "Red Bull Racing",
      "grid_position": null,
      "status": "",
      "points": 0
    },
    {
      "position": null,
      "driver": "SAR",
      "driver_number": 2,
      "team": "Williams",
      "grid_position": null,
      "status": "",
      "points": 0
    },
    {
      "position": null,
      "driver": "NOR",
      "driver_number": 4,
      "team": "McLaren",
      "grid_position": null,
      "status": "",
      "points": 0
    },
    {
      "position": null,
      "driver": "GAS",
      "driver_number": 10,
      "team": "Alpine",
      "grid_position": null,
      "status": "",
      "points": 0
    },
    {
      "position": null,
      "driver": "PER",
      "driver_number": 11,
      "team": "Red Bull Racing",
      "grid_position": null,
      "status": "",
      "points": 0
    },
    {
      "position": null,
      "driver": "ALO",
      "driver_number": 14,
      "team": "Aston Martin",
      "grid_position": null,
      "status": "",
      "points": 0
    },
    {
      "position": null,
      "driver": "LEC",
      "driver_number": 16,
      "team": "Ferrari",
      "grid_position": null,
      "status": "",
      "points": 0
    },
    {
      "position": null,
      "driver": "STR",
      "driver_number": 18,
      "team": "Aston Martin",
      "grid_position": null,
      "status": "",
      "points": 0
    },
    {
      "position": null,
      "driver": "MAG",
      "driver_number": 20,
      "team": "Haas F1 Team",
      "grid_position": null,
      "status": "",
      "points": 0
    },
    {
      "position": null,
      "driver": "DEV",
      "driver_number": 21,
      "team": "AlphaTauri",
      "grid_position": null,
      "status": "",
      "points": 0
    },
    {
      "position": null,
      "driver": "TSU",
      "driver_number": 22,
      "team": "AlphaTauri",
      "grid_position": null,
      "status": "",
      "points": 0
    },
    {
      "position": null,
      "driver": "ALB",
      "driver_number": 23,
      "team": "Williams",
      "grid_position": null,
      "status": "",
      "points": 0
    },
    {
      "position": null,
      "driver": "ZHO",
      "driver_number": 24,
      "team": "Alfa Romeo",
      "grid_position": null,
      "status": "",
      "points": 0
    },
    {
      "position": null,
      "driver": "HUL",
      "driver_number": 27,
      "team": "Haas F1 Team",
      "grid_position": null,
      "status": "",
      "points": 0
    },
    {
      "position": null,
      "driver": "OCO",
      "driver_number": 31,
      "team": "Alpine",
      "grid_position": null,
      "status": "",
      "points": 0
    },
    {
      "position": null,
      "driver": "HAM",
      "driver_number": 44,
      "team": "Mercedes",
      "grid_position": null,
      "status": "",
      "points": 0
    },
    {
      "position": null,
      "driver": "SAI",
      "driver_number": 55,
      "team": "Ferrari",
      "grid_position": null,
      "status": "",
      "points": 0
    },
    {
      "position": null,
      "driver": "RUS",
      "driver_number": 63,
      "team": "Mercedes",
      "grid_position": null,
      "status": "",
      "points": 0
    },
    {
      "position": null,
      "driver": "BOT",
      "driver_number": 77,
      "team": "Alfa Romeo",
      "grid_position": null,
      "status": "",
      "points": 0
    },
    {
      "position": null,
      "driver": "PIA",
      "driver_number": 81,
      "team": "McLaren",
      "grid_position": null,
      "status": "",
      "points": 0
    }
  ],
  "weather": {
    "air_temp": 14.802666666666667,
    "track_temp": 17.473333333333333,
    "humidity": 90.70666666666666,
    "rainfall": true,
    "wind_speed": 2.021333333333333
  },
  "fetched_at": "2026-05-21T21:10:23.593062"
}