{
  "session_type": "Q",
  "session_name": "Qualifying",
  "year": 2025,
  "round": 22,
  "gp_name": "Las Vegas Grand Prix",
  "date": "2025-11-22",
  "track": "Las Vegas",
  "country": "United States",
  "best_times": {
    "NOR": 107.934,
    "VER": 108.257,
    "SAI": 108.296,
    "RUS": 108.803,
    "PIA": 108.961,
    "LAW": 109.062,
    "ALO": 109.466,
    "HAD": 109.554,
    "LEC": 109.872,
    "GAS": 111.54,
    "HUL": 112.781,
    "STR": 112.85,
    "OCO": 112.987,
    "BEA": 113.094,
    "COL": 113.683,
    "ALB": 116.22,
    "ANT": 116.314,
    "BOR": 116.674,
    "TSU": 116.798,
    "HAM": 117.115
  },
  "results": [
    {
      "position": 1,
      "driver": "NOR",
      "driver_number": 4,
      "team": "McLaren",
      "grid_position": null,
      "status": "",
      "points": 0,
      "q1": 115.473,
      "q2": 111.379,
      "q3": 107.934
    },
    {
      "position": 2,
      "driver": "VER",
      "driver_number": 1,
      "team": "Red Bull Racing",
      "grid_position": null,
      "status": "",
      "points": 0,
      "q1": 113.458,
      "q2": 111.593,
      "q3": 108.257
    },
    {
      "position": 3,
      "driver": "SAI",
      "driver_number": 55,
      "team": "Williams",
      "grid_position": null,
      "status": "",
      "points": 0,
      "q1": 114.873,
      "q2": 111.144,
      "q3": 108.296
    },
    {
      "position": 4,
      "driver": "RUS",
      "driver_number": 63,
      "team": "Mercedes",
      "grid_position": null,
      "status": "",
      "points": 0,
      "q1": 113.144,
      "q2": 110.935,
      "q3": 108.803
    },
    {
      "position": 5,
      "driver": "PIA",
      "driver_number": 81,
      "team": "McLaren",
      "grid_position": null,
      "status": "",
      "points": 0,
      "q1": 114.544,
      "q2": 112.126,
      "q3": 108.961
    },
    {
      "position": 6,
      "driver": "LAW",
      "driver_number": 30,
      "team": "Racing Bulls",
      "grid_position": null,
      "status": "",
      "points": 0,
      "q1": 114.828,
      "q2": 111.621,
      "q3": 109.062
    },
    {
      "position": 7,
      "driver": "ALO",
      "driver_number": 14,
      "team": "Aston Martin",
      "grid_position": null,
      "status": "",
      "points": 0,
      "q1": 113.739,
      "q2": 111.865,
      "q3": 109.466
    },
    {
      "position": 8,
      "driver": "HAD",
      "driver_number": 6,
      "team": "Racing Bulls",
      "grid_position": null,
      "status": "",
      "points": 0,
      "q1": 115.613,
      "q2": 111.12,
      "q3": 109.554
    },
    {
      "position": 9,
      "driver": "LEC",
      "driver_number": 16,
      "team": "Ferrari",
      "grid_position": null,
      "status": "",
      "points": 0,
      "q1": 114.814,
      "q2": 111.952,
      "q3": 109.872
    },
    {
      "position": 10,
      "driver": "GAS",
      "driver_number": 10,
      "team": "Alpine",
      "grid_position": null,
      "status": "",
      "points": 0,
      "q1": 114.432,
      "q2": 111.76,
      "q3": 111.54
    },
    {
      "position": 11,
      "driver": "HUL",
      "driver_number": 27,
      "team": "Kick Sauber",
      "grid_position": null,
      "status": "",
      "points": 0,
      "q1": 114.555,
      "q2": 112.781
    },
    {
      "position": 12,
      "driver": "STR",
      "driver_number": 18,
      "team": "Aston Martin",
      "grid_position": null,
      "status": "",
      "points": 0,
      "q1": 114.416,
      "q2": 112.85
    },
    {
      "position": 13,
      "driver": "OCO",
      "driver_number": 31,
      "team": "Haas F1 Team",
      "grid_position": null,
      "status": "",
      "points": 0,
      "q1": 114.635,
      "q2": 112.987
    },
    {
      "position": 14,
      "driver": "BEA",
      "driver_number": 87,
      "team": "Haas F1 Team",
      "grid_position": null,
      "status": "",
      "points": 0,
      "q1": 116.016,
      "q2": 113.094
    },
    {
      "position": 15,
      "driver": "COL",
      "driver_number": 43,
      "team": "Alpine",
      "grid_position": null,
      "status": "",
      "points": 0,
      "q1": 114.847,
      "q2": 113.683
    },
    {
      "position": 16,
      "driver": "ALB",
      "driver_number": 23,
      "team": "Williams",
      "grid_position": null,
      "status": "",
      "points": 0,
      "q1": 116.22
    },
    {
      "position": 17,
      "driver": "ANT",
      "driver_number": 12,
      "team": "Mercedes",
      "grid_position": null,
      "status": "",
      "points": 0,
      "q1": 116.314
    },
    {
      "position": 18,
      "driver": "BOR",
      "driver_number": 5,
      "team": "Kick Sauber",
      "grid_position": null,
      "status": "",
      "points": 0,
      "q1": 116.674
    },
    {
      "position": 19,
      "driver": "TSU",
      "driver_number": 22,
      "team": "Red Bull Racing",
      "grid_position": null,
      "status": "",
      "points": 0,
      "q1": 116.798
    },
    {
      "position": 20,
      "driver": "HAM",
      "driver_number": 44,
      "team": "Ferrari",
      "grid_position": null,
      "status": "",
      "points": 0,
      "q1": 117.115
    }
  ],
  "weather": {
    "air_temp": 11.728235294117646,
    "track_temp": 12.549411764705884,
    "humidity": 65.54117647058824,
    "rainfall": true,
    "wind_speed": 1.5764705882352938
  },
  "fetched_at": "2026-05-21T23:30:09.803066"
}