{
  "session_type": "FP2",
  "session_name": "Practice 2",
  "year": 2025,
  "round": 11,
  "gp_name": "Austrian Grand Prix",
  "date": "2025-06-27",
  "track": "Spielberg",
  "country": "Austria",
  "best_times": {
    "VER": 64.898,
    "NOR": 64.58,
    "BOR": 65.411,
    "HAD": 65.547,
    "GAS": 65.613,
    "ANT": 65.537,
    "ALO": 65.457,
    "LEC": 65.19,
    "STR": 65.022,
    "TSU": 65.292,
    "ALB": 65.765,
    "HUL": 65.918,
    "LAW": 65.543,
    "OCO": 65.698,
    "COL": 66.176,
    "HAM": 65.511,
    "SAI": 65.814,
    "RUS": 65.229,
    "PIA": 64.737,
    "BEA": 65.835
  },
  "results": [
    {
      "position": null,
      "driver": "VER",
      "driver_number": 1,
      "team": "Red Bull Racing",
      "grid_position": null,
      "status": "",
      "points": 0
    },
    {
      "position": null,
      "driver": "NOR",
      "driver_number": 4,
      "team": "McLaren",
      "grid_position": null,
      "status": "",
      "points": 0
    },
    {
      "position": null,
      "driver": "BOR",
      "driver_number": 5,
      "team": "Kick Sauber",
      "grid_position": null,
      "status": "",
      "points": 0
    },
    {
      "position": null,
      "driver": "HAD",
      "driver_number": 6,
      "team": "Racing Bulls",
      "grid_position": null,
      "status": "",
      "points": 0
    },
    {
      "position": null,
      "driver": "GAS",
      "driver_number": 10,
      "team": "Alpine",
      "grid_position": null,
      "status": "",
      "points": 0
    },
    {
      "position": null,
      "driver": "ANT",
      "driver_number": 12,
      "team": "Mercedes",
      "grid_position": null,
      "status": "",
      "points": 0
    },
    {
      "position": null,
      "driver": "ALO",
      "driver_number": 14,
      "team": "Aston Martin",
      "grid_position": null,
      "status": "",
      "points": 0
    },
    {
      "position": null,
      "driver": "LEC",
      "driver_number": 16,
      "team": "Ferrari",
      "grid_position": null,
      "status": "",
      "points": 0
    },
    {
      "position": null,
      "driver": "STR",
      "driver_number": 18,
      "team": "Aston Martin",
      "grid_position": null,
      "status": "",
      "points": 0
    },
    {
      "position": null,
      "driver": "TSU",
      "driver_number": 22,
      "team": "Red Bull Racing",
      "grid_position": null,
      "status": "",
      "points": 0
    },
    {
      "position": null,
      "driver": "ALB",
      "driver_number": 23,
      "team": "Williams",
      "grid_position": null,
      "status": "",
      "points": 0
    },
    {
      "position": null,
      "driver": "HUL",
      "driver_number": 27,
      "team": "Kick Sauber",
      "grid_position": null,
      "status": "",
      "points": 0
    },
    {
      "position": null,
      "driver": "LAW",
      "driver_number": 30,
      "team": "Racing Bulls",
      "grid_position": null,
      "status": "",
      "points": 0
    },
    {
      "position": null,
      "driver": "OCO",
      "driver_number": 31,
      "team": "Haas F1 Team",
      "grid_position": null,
      "status": "",
      "points": 0
    },
    {
      "position": null,
      "driver": "COL",
      "driver_number": 43,
      "team": "Alpine",
      "grid_position": null,
      "status": "",
      "points": 0
    },
    {
      "position": null,
      "driver": "HAM",
      "driver_number": 44,
      "team": "Ferrari",
      "grid_position": null,
      "status": "",
      "points": 0
    },
    {
      "position": null,
      "driver": "SAI",
      "driver_number": 55,
      "team": "Williams",
      "grid_position": null,
      "status": "",
      "points": 0
    },
    {
      "position": null,
      "driver": "RUS",
      "driver_number": 63,
      "team": "Mercedes",
      "grid_position": null,
      "status": "",
      "points": 0
    },
    {
      "position": null,
      "driver": "PIA",
      "driver_number": 81,
      "team": "McLaren",
      "grid_position": null,
      "status": "",
      "points": 0
    },
    {
      "position": null,
      "driver": "BEA",
      "driver_number": 87,
      "team": "Haas F1 Team",
      "grid_position": null,
      "status": "",
      "points": 0
    }
  ],
  "weather": {
    "air_temp": 25.46708860759494,
    "track_temp": 36.3367088607595,
    "humidity": 38.11392405063291,
    "rainfall": false,
    "wind_speed": 1.1772151898734178
  },
  "fetched_at": "2026-05-21T23:18:47.943571"
}